massgenotyping/__about__.py
massgenotyping/__init__.py
massgenotyping/allele_call.py
massgenotyping/allele_check.py
massgenotyping/argument_parser.py
massgenotyping/base.py
massgenotyping/demultiplex.py
massgenotyping/denoise.py
massgenotyping/find_ssrs.py
massgenotyping/merge_pairs.py
massgenotyping/show_alignment.py
massgenotyping/trim_sequence.py
massgenotyping/utils.py
massgenotyping/variant_filter.py
massgenotyping-0.2.2.dist-info/METADATA
massgenotyping-0.2.2.dist-info/WHEEL
massgenotyping-0.2.2.dist-info/entry_points.txt
massgenotyping-0.2.2.dist-info/licenses/LICENSE
massgenotyping-0.2.2.dist-info/RECORD
