Metadata-Version: 2.1
Name: massgenotyping
Version: 0.2.2
Summary: Python package for microsatellite genotyping from amplicon sequencing data
Project-URL: Documentation, https://github.com/kohyamat/massgenotyping#readme
Project-URL: Issues, https://github.com/kohyamat/massgenotyping/issues
Project-URL: Source, https://github.com/kohyamat/massgenotyping
Author: Tetsuo Kohyama
Author-email: tetsuo.kohyama@gmil.com
License: MIT
License-File: LICENSE
Keywords: NGS,amplicon sequencing,genotyping,microsatellite
Classifier: Development Status :: 4 - Beta
Classifier: License :: OSI Approved :: MIT License
Classifier: Programming Language :: Python
Classifier: Programming Language :: Python :: 3.8
Classifier: Programming Language :: Python :: 3.9
Classifier: Programming Language :: Python :: 3.10
Classifier: Programming Language :: Python :: 3.11
Classifier: Programming Language :: Python :: 3.12
Requires-Python: >=3.8
Requires-Dist: biopython
Requires-Dist: dataclasses-json
Requires-Dist: fuzzysearch
Requires-Dist: matplotlib
Requires-Dist: natsort
Requires-Dist: numpy
Requires-Dist: pandas
Requires-Dist: python-levenshtein
Requires-Dist: seaborn
Requires-Dist: tqdm
